skscope-0.1.8.dist-info/RECORD
skscope-0.1.8.dist-info/LICENSE
skscope-0.1.8.dist-info/WHEEL
skscope-0.1.8.dist-info/top_level.txt
skscope-0.1.8.dist-info/METADATA
skscope/base_solver.py
skscope/solver.py
skscope/__init__.py
skscope/_scope.cpython-312-darwin.so
skscope/layer.py
skscope/utilities.py
skscope/skmodel.py
skscope/numeric_solver.py
