Metadata-Version: 2.1
Name: skscope
Version: 0.1.8
Summary: Sparsity-Constraint OPtimization via itErative-algorithm
Home-page: https://skscope.readthedocs.io
Download-URL: https://pypi.python.org/pypi/skscope
Author: Zezhi Wang, Jin Zhu,
Author-email: homura@mail.ustc.edu.cn
Maintainer: Zezhi Wang
Maintainer-email: homura@mail.ustc.edu.cn
License: MIT
Project-URL: Bug Tracker, https://github.com/abess-team/skscope/issues
Project-URL: Documentation, https://skscope.readthedocs.io
Project-URL: Source Code, https://github.com/abess-team/skscope
Classifier: Intended Audience :: Science/Research
Classifier: Intended Audience :: Developers
Classifier: Programming Language :: C++
Classifier: Programming Language :: Python
Classifier: Topic :: Software Development
Classifier: Topic :: Scientific/Engineering
Classifier: Topic :: Scientific/Engineering :: Artificial Intelligence
Classifier: Topic :: Scientific/Engineering :: Mathematics
Classifier: Operating System :: Microsoft :: Windows
Classifier: Operating System :: POSIX :: Linux
Classifier: Operating System :: MacOS
Classifier: Programming Language :: Python
Classifier: Programming Language :: Python :: 3.8
Classifier: Programming Language :: Python :: 3.9
Classifier: Programming Language :: Python :: 3.10
Classifier: Programming Language :: Python :: 3.11
Requires-Python: >=3.8
License-File: LICENSE
Requires-Dist: numpy
Requires-Dist: scikit-learn>=1.2.2
Requires-Dist: jax[cpu]
Requires-Dist: scipy
